{
    "id": "",
    "sceneNumber": 0,
    "baseUrl": "",
    "baseUrlBundles": "",
    "contents": [],
    "basePosition": {
        "x": 0,
        "y": 0
    },
    "parcels": [],
    "sdk7": false,
    "requiredPermissions": [],
    "allowedMediaHostnames": [],
    "loadingScreenHints": [
        {
            "textureUrl": "https://api.decentraland.org/v1/minimap.png",
            "title": "local hint title 01",
            "body": "local hint body 1 where you can put a lot of text just to be sure that the hints are working as expected",
            "sourceTag": 2
        },
        {
          "textureUrl": "https://api.decentraland.org/v1/estatemap.png",
          "title": "local hint title 02",
          "body": "local hint body 2222222 where you can put a lot of text just to be sure that the hints are working as expected",
          "sourceTag": 2
        },
        {
          "textureUrl": "https://api.decentraland.org/v1/broken-map.png",
          "title": "03 hint 404 error test",
          "body": "local hint body. This is a test for a 404 error when trying to load the image.",
          "sourceTag": 2
        }
    ]
}
